MANIFEST.in
README.txt
setup.cfg
setup.py
docs/HISTORY.txt
haufe/__init__.py
haufe.hrs.configuration.egg-info/PKG-INFO
haufe.hrs.configuration.egg-info/SOURCES.txt
haufe.hrs.configuration.egg-info/dependency_links.txt
haufe.hrs.configuration.egg-info/entry_points.txt
haufe.hrs.configuration.egg-info/namespace_packages.txt
haufe.hrs.configuration.egg-info/not-zip-safe
haufe.hrs.configuration.egg-info/requires.txt
haufe.hrs.configuration.egg-info/top_level.txt
haufe/hrs/__init__.py
haufe/hrs/configuration/__init__.py
haufe/hrs/configuration/configure.zcml
haufe/hrs/configuration/decorator.py
haufe/hrs/configuration/demo.py
haufe/hrs/configuration/demo2_notify.py
haufe/hrs/configuration/interfaces.py
haufe/hrs/configuration/logger.py
haufe/hrs/configuration/meta.zcml
haufe/hrs/configuration/patches.py
haufe/hrs/configuration/service.py
haufe/hrs/configuration/services.py
haufe/hrs/configuration/util.py
haufe/hrs/configuration/zcml.py
haufe/hrs/configuration/example/model/cms.ini
haufe/hrs/configuration/example/model/toolbox.ini
haufe/hrs/configuration/example/sample_config/all-in-one.ini
haufe/hrs/configuration/example/sample_config/modular-cms.ini
haufe/hrs/configuration/example/sample_config/modular-config.ini
haufe/hrs/configuration/example/sample_config/modular-toolbox.ini
haufe/hrs/configuration/tests/__init__.py
haufe/hrs/configuration/tests/example.zcml
haufe/hrs/configuration/tests/test_configuration.py
haufe/hrs/configuration/tests/test_directives.py
haufe/hrs/configuration/tests/test_service.py