Metadata-Version: 1.0
Name: haufe.hrs.configuration
Version: 0.5.18
Summary: A central configuration service for Zope 2/3-based applications  based on a pseudo-hierarchical INI-file format with model support for defining the configuration schema
Home-page: UNKNOWN
Author: Andreas Jung
Author-email: info@zopyx.com
License: ZPL
Keywords: Zope Configuration
Platform: UNKNOWN
Classifier: Programming Language :: Python
Classifier: Topic :: Software Development :: Libraries :: Python Modules
Classifier: Framework :: Zope2
Classifier: Framework :: Zope3
Classifier: License :: OSI Approved :: Zope Public License
Classifier: Intended Audience :: Developers
